__init__.py
imagedata/__init__.py
imagedata/axis.py
imagedata/cmdline.py
imagedata/collection.py
imagedata/header.py
imagedata/image_data.py
imagedata/list_plugins.py
imagedata/readdata.py
imagedata/series.py
imagedata/viewer.py
imagedata/apps/__init__.py
imagedata/apps/diffusion.py
imagedata/apps/Siemens/ROI.py
imagedata/apps/Siemens/__init__.py
imagedata/apps/Siemens/draw_antialiased.py
imagedata/apps/Siemens/evidence2mask.py
imagedata/apps/Siemens/evidence_main.py
imagedata/archives/__init__.py
imagedata/archives/abstractarchive.py
imagedata/archives/filesystemarchive.py
imagedata/archives/zipfilearchive.py
imagedata/formats/__init__.py
imagedata/formats/abstractplugin.py
imagedata/formats/dicomplugin.py
imagedata/formats/itkplugin.py
imagedata/formats/matplugin.py
imagedata/formats/niftiplugin.py
imagedata/formats/dicomlib/__init__.py
imagedata/formats/dicomlib/uid.py
imagedata/transports/__init__.py
imagedata/transports/abstracttransport.py
imagedata/transports/dicomtransport.py
imagedata/transports/filetransport.py
imagedata/transports/xnattransport.py
imagedata-3.8.13.dist-info/licenses/LICENSE.txt
imagedata-3.8.13.dist-info/METADATA
imagedata-3.8.13.dist-info/WHEEL
imagedata-3.8.13.dist-info/entry_points.txt
imagedata-3.8.13.dist-info/top_level.txt
imagedata-3.8.13.dist-info/RECORD
