Metadata-Version: 2.4
Name: imagedata
Version: 3.8.13
Summary: Read/write medical image data
Author-email: Erling Andersen <Erling.Andersen@Helse-Bergen.NO>
Maintainer-email: Erling Andersen <Erling.Andersen@Helse-Bergen.NO>
License: MIT License
Project-URL: Homepage, https://github.com/erling6232/imagedata
Project-URL: Documentation, https://imagedata.readthedocs.io
Project-URL: Source Code, https://github.com/erling6232/imagedata
Keywords: dicom,python,medical,imaging,pydicom,pynetdicom,itk
Classifier: Programming Language :: Python :: 3.9
Classifier: Programming Language :: Python :: 3.10
Classifier: Programming Language :: Python :: 3.11
Classifier: Programming Language :: Python :: 3.12
Classifier: Programming Language :: Python :: 3.13
Classifier: Development Status :: 4 - Beta
Classifier: Environment :: Other Environment
Classifier: Intended Audience :: Developers
Classifier: Intended Audience :: Healthcare Industry
Classifier: Intended Audience :: Science/Research
Classifier: License :: OSI Approved :: MIT License
Classifier: Operating System :: OS Independent
Classifier: Topic :: Software Development :: Libraries :: Python Modules
Classifier: Topic :: Scientific/Engineering :: Medical Science Apps.
Requires-Python: <3.14,>=3.9
License-File: LICENSE.txt
Requires-Dist: pydicom>=2.4.0
Requires-Dist: pylibjpeg[all]
Requires-Dist: pynetdicom<2,>=1.2.0
Requires-Dist: itk-io>=5.4.0
Requires-Dist: scikit-build-core
Requires-Dist: nibabel>=5.0.0
Requires-Dist: numpy>=1.22.2
Requires-Dist: pandas
Requires-Dist: scipy>=1.2.4
Requires-Dist: python-magic
Requires-Dist: python-magic-bin; platform_system == "Windows"
Requires-Dist: imageio
Requires-Dist: pillow>=10.0.0
Requires-Dist: xnat<0.7
Requires-Dist: matplotlib>=3.8.0
Requires-Dist: opencv-python-headless
Dynamic: license-file
